LICENSE.txt
MANIFEST.in
README.md
setup.py
chillapi/__init__.py
chillapi/abc.py
chillapi/api.py
chillapi/api.schema.json
chillapi/manager.py
chillapi/requirements.txt
chillapi.egg-info/PKG-INFO
chillapi.egg-info/SOURCES.txt
chillapi.egg-info/dependency_links.txt
chillapi.egg-info/requires.txt
chillapi.egg-info/top_level.txt
chillapi/app/__init__.py
chillapi/app/config.py
chillapi/app/error_handlers.py
chillapi/app/file_utils.py
chillapi/app/forms.py
chillapi/app/robots.py
chillapi/app/sitemap.py
chillapi/app/flask_restful_swagger_3/__init__.py
chillapi/app/flask_restful_swagger_3/swagger.py
chillapi/database/__init__.py
chillapi/database/connection.py
chillapi/database/query_builder.py
chillapi/database/repository.py
chillapi/database/serializer.py
chillapi/endpoints/__init__.py
chillapi/endpoints/sql.py
chillapi/endpoints/tables.py
chillapi/endpoints/tables_utils.py
chillapi/exceptions/__init__.py
chillapi/exceptions/api_manager.py
chillapi/exceptions/http.py
chillapi/extensions/__init__.py
chillapi/extensions/audit.py
chillapi/extensions/events.py
chillapi/extensions/record_livecycle.py
chillapi/http/__init__.py
chillapi/http/utils.py
chillapi/logger/__init__.py
chillapi/logger/app_loggers.py
chillapi/logger/formatter.py
chillapi/swagger/__init__.py
chillapi/swagger/http.py
chillapi/swagger/jsonschema.py
chillapi/swagger/schemas.py
chillapi/swagger/utils.py