Metadata-Version: 2.1
Name: chillapi
Version: 0.0.1
Summary: A library to create APIs focused on data projects
Home-page: UNKNOWN
Author: andrescevp@gmail.com
License: MIT
Keywords: python,api,codeless,data
Platform: UNKNOWN
Requires-Python: >=3.8
Provides-Extra: testing
